dart_api_controller/__init__.py
dart_api_controller/__main__.py
dart_api_controller/alias_functions.py
dart_api_controller/aws_upload_utils.py
dart_api_controller/corp_consts.py
dart_api_controller/corpcode_exceptions.py
dart_api_controller/corpcode_preprocessor.py
dart_api_controller/corpcode_utils.py
dart_api_controller/dart_connector.py
dart_api_controller/dart_consts.py
dart_api_controller/dataset_loader.py
dart_api_controller/db_upload_utils.py
dart_api_controller/macro_utils.py
dart_api_controller/path_director.py
dart_api_controller/response_parser.py
dart_api_controller/xml_parser.py
dart_api_controller/xml_utils.py
dart_api_controller/disclosure_utils/__init__.py
dart_api_controller/disclosure_utils/disclosure_consts.py
dart_api_controller/disclosure_utils/disclosure_content_fetcher.py
dart_api_controller/disclosure_utils/disclosure_content_loader.py
dart_api_controller/disclosure_utils/disclosure_content_saver.py
dart_api_controller/disclosure_utils/disclosure_content_utils.py
dart_api_controller/disclosure_utils/disclosure_exceptions.py
dart_api_controller/disclosure_utils/disclosure_list_application.py
dart_api_controller/disclosure_utils/disclosure_list_fetcher.py
dart_api_controller/disclosure_utils/disclosure_list_utils.py
dart_api_controller/disclosure_utils/disclosure_path_director.py
dart_api_controller/disclosure_utils/disclosure_xml_loader.py
dart_api_controller/disclosure_utils/disclosure_xml_parser.py
dart_api_controller/result_utils/__init__.py
dart_api_controller/result_utils/result_consts.py
dart_api_controller/result_utils/result_loader.py
dart_api_controller/result_utils/result_path_director.py
dart_api_controller/result_utils/result_utils.py
dart_api_controller/result_utils/search_defined_benefit_liability_in_statement_footnote.py
dart_api_controller/result_utils/search_result_generator.py
dart_api_controller/result_utils/search_temp_conts.py
dart_api_controller/xml_contoller/__init__.py
dart_api_controller/xml_contoller/xml_loader.py
dart_api_controller-0.2.6.dist-info/METADATA
dart_api_controller-0.2.6.dist-info/WHEEL
dart_api_controller-0.2.6.dist-info/top_level.txt
dart_api_controller-0.2.6.dist-info/RECORD
