Metadata-Version: 2.2
Name: dart_api_controller
Version: 0.2.6
Summary: A Python package for interacting with DART (Data Analysis, Retrieval and Transfer) API
Home-page: https://github.com/nailen1/dart_api_controller
Author: June Young Park
Author-email: juneyoungpaak@gmail.com
Classifier: Development Status :: 3 - Alpha
Classifier: Intended Audience :: Financial and Insurance Industry
Classifier: License :: Free For Educational Use
Classifier: Programming Language :: Python :: 3
Classifier: Programming Language :: Python :: 3.11
Classifier: Topic :: Office/Business :: Financial
Classifier: Topic :: Software Development :: Libraries :: Python Modules
Requires-Python: >=3.11
Requires-Dist: pandas>=2.0.0
Requires-Dist: python-dotenv>=1.0.0
Requires-Dist: requests>=2.31.0
Requires-Dist: lxml>=4.9.0
Requires-Dist: tqdm>=4.65.0
Requires-Dist: python-dateutil>=2.8.2
Requires-Dist: openai>=1.0.0
Requires-Dist: boto3>=1.34.0
Requires-Dist: shining-pebbles>=0.4.3
Requires-Dist: canonical-transformer>=0.2.3
Requires-Dist: aws-s3-controller>=0.1.0
Requires-Dist: financial-dataset-preprocessor>=0.1.6
Requires-Dist: beautifulsoup4>=4.12.0
Dynamic: author
Dynamic: author-email
Dynamic: classifier
Dynamic: description
Dynamic: description-content-type
Dynamic: home-page
Dynamic: requires-dist
Dynamic: requires-python
Dynamic: summary
